README.md
setup.py
src/vdk/plugin/control_cli_plugin/control_service_api_error_decorator.py
src/vdk/plugin/control_cli_plugin/control_service_configuration.py
src/vdk/plugin/control_cli_plugin/control_service_properties_client.py
src/vdk/plugin/control_cli_plugin/control_service_secrets_client.py
src/vdk/plugin/control_cli_plugin/execution_skip.py
src/vdk/plugin/control_cli_plugin/properties_plugin.py
src/vdk/plugin/control_cli_plugin/secrets_plugin.py
src/vdk/plugin/control_cli_plugin/vdk_plugin_control_cli.py
src/vdk_plugin_control_cli.egg-info/PKG-INFO
src/vdk_plugin_control_cli.egg-info/SOURCES.txt
src/vdk_plugin_control_cli.egg-info/dependency_links.txt
src/vdk_plugin_control_cli.egg-info/entry_points.txt
src/vdk_plugin_control_cli.egg-info/requires.txt
src/vdk_plugin_control_cli.egg-info/top_level.txt
tests/test_control_service_properties.py
tests/test_execution_skip.py
tests/test_properties_plugin.py
tests/test_secrets_plugin.py
tests/test_vdk_plugin_control_cli.py