Metadata-Version: 2.1
Name: vdk-plugin-control-cli
Version: 0.1.928743296
Summary: Versatile Data Kit SDK plugin exposing CLI commands for managing the lifecycle of a Data Jobs.
Home-page: https://github.com/vmware/versatile-data-kit
Classifier: Development Status :: 4 - Beta
Classifier: License :: OSI Approved :: Apache Software License
Classifier: Programming Language :: Python :: 3.7
Classifier: Programming Language :: Python :: 3.8
Classifier: Programming Language :: Python :: 3.9
Classifier: Programming Language :: Python :: 3.10
Classifier: Programming Language :: Python :: 3.11
